flask_githubcard/__init__.py
flask_githubcard/static/css/bootstrap.min.darkly.css
flask_githubcard/static/css/bootstrap.min.default.css
flask_githubcard/static/js/bootstrap.min.js
flask_githubcard/static/js/bootstrap.min.js.map
flask_githubcard/static/js/jquery-3.6.0.min.js
flask_githubcard/static/js/jquery-3.6.0.min.map
Flask_Githubcard-1.0.4.dist-info/LICENSE
Flask_Githubcard-1.0.4.dist-info/METADATA
Flask_Githubcard-1.0.4.dist-info/WHEEL
Flask_Githubcard-1.0.4.dist-info/top_level.txt
Flask_Githubcard-1.0.4.dist-info/RECORD
