Metadata-Version: 2.1
Name: Flask-Githubcard
Version: 1.0.4
Summary: Generator a github card for flask web application
Home-page: https://2dogz.cn
Author: jiangwei
Author-email: qq804022023@gmail.com
License: Apache Software License
Keywords: flask extension development
Platform: any
Classifier: Environment :: Web Environment
Classifier: Intended Audience :: Developers
Classifier: License :: OSI Approved :: Apache Software License
Classifier: Operating System :: OS Independent
Classifier: Programming Language :: Python
Classifier: Topic :: Internet :: WWW/HTTP :: Dynamic Content
Classifier: Topic :: Software Development :: Libraries :: Python Modules
Requires-Dist: Flask
Requires-Dist: Requests
